taotools/__init__.py
taotools_happyctest-0.0.1.dist-info/LICENSE
taotools_happyctest-0.0.1.dist-info/METADATA
taotools_happyctest-0.0.1.dist-info/WHEEL
taotools_happyctest-0.0.1.dist-info/top_level.txt
taotools_happyctest-0.0.1.dist-info/RECORD
